Metadata-Version: 2.1
Name: memphis-functions-beta
Version: 1.0.2
Summary: A powerful messaging platform for modern developers
Home-page: https://github.com/memphisdev/memphis-functions.py
Author: Memphis.dev
Author-email: team@memphis.dev
License: Apache-2.0
Download-URL: https://github.com/memphisdev/memphis-functions.py/archive/refs/tags/1.0.2.tar.gz
Keywords: message broker,devtool,streaming,data
Platform: UNKNOWN
Classifier: Development Status :: 4 - Beta
Classifier: Intended Audience :: Developers
Classifier: Topic :: Software Development
Classifier: License :: OSI Approved :: GNU General Public License (GPL)
Classifier: Programming Language :: Python :: 3.7
Classifier: Programming Language :: Python :: 3.8
Classifier: Programming Language :: Python :: 3.9
Classifier: Programming Language :: Python :: 3.10
Classifier: Programming Language :: Python :: 3.11
Classifier: Programming Language :: Python :: 3.12
License-File: LICENSE
License-File: LICENSE.txt
